calculuskit/__init__.py
calculuskit/py.typed
calculuskit/derivative/__init__.py
calculuskit/derivative/derivative.py
calculuskit/double_integral/__init__.py
calculuskit/double_integral/double_integral.py
calculuskit/fourier_series/__init__.py
calculuskit/fourier_series/fourier_series.py
calculuskit/integral/__init__.py
calculuskit/integral/integral.py
calculuskit/limit/__init__.py
calculuskit/limit/limit.py
calculuskit/maclaurin_series/__init__.py
calculuskit/maclaurin_series/maclaurin_series.py
calculuskit/partial_derivative/__init__.py
calculuskit/partial_derivative/partial_derivative.py
calculuskit/plotter/__init__.py
calculuskit/plotter/animation_plotter.py
calculuskit/plotter/base_plotter.py
calculuskit/plotter/plotter.py
calculuskit/plotter/plotter_2d.py
calculuskit/plotter/plotter_3d.py
calculuskit/plotter/vector_field_plotter.py
calculuskit/taylor_series/__init__.py
calculuskit/taylor_series/taylor_series.py
calculuskit-0.1.0.dist-info/licenses/LICENSE
calculuskit-0.1.0.dist-info/METADATA
calculuskit-0.1.0.dist-info/WHEEL
calculuskit-0.1.0.dist-info/top_level.txt
calculuskit-0.1.0.dist-info/RECORD
