Metadata-Version: 2.4
Name: calculuskit
Version: 0.1.0
Summary: A Python library for mathematical calculus operations
Author-email: Mohamed Sajith <your.email@example.com>
License: MIT
Project-URL: Homepage, https://github.com/mohamedsajith/calculuskit
Project-URL: Documentation, https://github.com/mohamedsajith/calculuskit#readme
Project-URL: Repository, https://github.com/mohamedsajith/calculuskit
Project-URL: Bug Tracker, https://github.com/mohamedsajith/calculuskit/issues
Keywords: calculus,mathematics,derivatives,integrals,limits,numerical-analysis
Classifier: Development Status :: 3 - Alpha
Classifier: Intended Audience :: Developers
Classifier: Intended Audience :: Science/Research
Classifier: License :: OSI Approved :: MIT License
Classifier: Operating System :: OS Independent
Classifier: Programming Language :: Python :: 3
Classifier: Programming Language :: Python :: 3.8
Classifier: Programming Language :: Python :: 3.9
Classifier: Programming Language :: Python :: 3.10
Classifier: Programming Language :: Python :: 3.11
Classifier: Programming Language :: Python :: 3.12
Classifier: Topic :: Scientific/Engineering :: Mathematics
Classifier: Typing :: Typed
Requires-Python: >=3.8
License-File: LICENSE
Requires-Dist: numpy>=1.20.0
Requires-Dist: matplotlib>=3.5.0
Provides-Extra: dev
Requires-Dist: pytest>=7.0; extra == "dev"
Requires-Dist: pytest-cov>=4.0; extra == "dev"
Requires-Dist: ruff>=0.1.0; extra == "dev"
Requires-Dist: mypy>=1.0; extra == "dev"
Requires-Dist: pre-commit>=3.0; extra == "dev"
Dynamic: license-file
